hier_config_cli/__init__.py
hier_config_cli/__main__.py
hier_config_cli/py.typed
hier_config_cli-0.2.0.dist-info/LICENSE
hier_config_cli-0.2.0.dist-info/METADATA
hier_config_cli-0.2.0.dist-info/WHEEL
hier_config_cli-0.2.0.dist-info/entry_points.txt
hier_config_cli-0.2.0.dist-info/RECORD
