Metadata-Version: 2.3
Name: hier-config-cli
Version: 0.2.0
Summary: A command-line interface tool for network configuration analysis, remediation, and rollback built on top of the Hier Config library
License: Apache-2.0
Keywords: network,automation,configuration,cisco,juniper,arista
Author: James Williams
Author-email: james.williams@packetgeek.net
Requires-Python: >=3.10,<4.0
Classifier: Development Status :: 4 - Beta
Classifier: Intended Audience :: Developers
Classifier: Intended Audience :: System Administrators
Classifier: License :: OSI Approved :: Apache Software License
Classifier: Programming Language :: Python :: 3
Classifier: Programming Language :: Python :: 3.10
Classifier: Programming Language :: Python :: 3.11
Classifier: Programming Language :: Python :: 3.12
Classifier: Programming Language :: Python :: 3.13
Classifier: Topic :: System :: Networking
Classifier: Topic :: System :: Systems Administration
Requires-Dist: click (>=8.1.7,<9.0.0)
Requires-Dist: hier-config (>=3.3.0,<4.0.0)
Requires-Dist: pyyaml (>=6.0.2,<7.0.0)
Project-URL: Homepage, https://github.com/netdevops/hier-config-cli
Project-URL: Repository, https://github.com/netdevops/hier-config-cli
